purplship/mappers/ups/__init__.py
purplship/mappers/ups/mapper.py
purplship/mappers/ups/proxy.py
purplship/mappers/ups/settings.py
purplship/providers/ups/__init__.py
purplship/providers/ups/address.py
purplship/providers/ups/error.py
purplship/providers/ups/pickup/__init__.py
purplship/providers/ups/pickup/cancel.py
purplship/providers/ups/pickup/create.py
purplship/providers/ups/pickup/rate.py
purplship/providers/ups/pickup/update.py
purplship/providers/ups/rate.py
purplship/providers/ups/shipment/__init__.py
purplship/providers/ups/shipment/cancel.py
purplship/providers/ups/shipment/create.py
purplship/providers/ups/tracking.py
purplship/providers/ups/units.py
purplship/providers/ups/utils.py
purplship.ups-2022.2.dist-info/WHEEL
purplship.ups-2022.2.dist-info/METADATA
purplship.ups-2022.2.dist-info/RECORD
